Metadata-Version: 2.1
Name: MarkoLib
Version: 0.2
Summary: Marko Programming
Author: Marko
Author-email: fhdhasd3232@gmail.com
Classifier: Programming Language :: Python :: 3
Classifier: Operating System :: OS Independent
Classifier: License :: OSI Approved :: MIT License
